itunessmart/__init__.py
itunessmart/__main__.py
itunessmart/_version.py
itunessmart/data_structure.py
itunessmart/library.py
itunessmart/parse.py
itunessmart/xsp.py
itunessmart/xsp_structure.py
itunessmart-1.1.9.dist-info/licenses/LICENSE
itunessmart-1.1.9.dist-info/METADATA
itunessmart-1.1.9.dist-info/WHEEL
itunessmart-1.1.9.dist-info/top_level.txt
itunessmart-1.1.9.dist-info/zip-safe
itunessmart-1.1.9.dist-info/RECORD
