Metadata-Version: 2.4
Name: itunessmart
Version: 1.1.9
Summary: Decode iTunes Smart playlist rules. Convert iTunes smart playlists to Kodi xsp smart playlists.
Author-email: cuzi <cuzi@openmail.cc>
License: MIT
Project-URL: Homepage, https://github.com/cvzi/itunes_smartplaylist
Classifier: Programming Language :: Python
Classifier: Programming Language :: Python :: 3
Classifier: Programming Language :: Python :: 3.8
Classifier: Programming Language :: Python :: 3.9
Classifier: Programming Language :: Python :: 3.10
Classifier: Programming Language :: Python :: 3.11
Classifier: Programming Language :: Python :: 3.12
Classifier: Programming Language :: Python :: 3.13
Classifier: License :: OSI Approved :: MIT License
Classifier: Operating System :: MacOS :: MacOS X
Classifier: Operating System :: Microsoft :: Windows
Classifier: Topic :: Multimedia :: Sound/Audio
Classifier: Topic :: Multimedia :: Sound/Audio :: Players
License-File: LICENSE
Provides-Extra: testing
Requires-Dist: pytest; extra == "testing"
Dynamic: license-file
